apispirit/__init__.py
apispirit/__main__.py
apispirit-0.1.0.dist-info/LICENSE
apispirit-0.1.0.dist-info/METADATA
apispirit-0.1.0.dist-info/WHEEL
apispirit-0.1.0.dist-info/entry_points.txt
apispirit-0.1.0.dist-info/top_level.txt
apispirit-0.1.0.dist-info/RECORD
