Metadata-Version: 2.1
Name: apispirit
Version: 0.1.0
License: Apache 2.0
Project-URL: Repository, https://github.com/kerstenbreuer/app
License-File: LICENSE
